gigasmol/__init__.py
gigasmol/models.py
gigasmol/gigachat_api/__init__.py
gigasmol/gigachat_api/api_model.py
gigasmol/gigachat_api/auth.py
gigasmol-0.0.8.dist-info/licenses/LICENSE
gigasmol-0.0.8.dist-info/METADATA
gigasmol-0.0.8.dist-info/WHEEL
gigasmol-0.0.8.dist-info/top_level.txt
gigasmol-0.0.8.dist-info/RECORD
