Metadata-Version: 2.4
Name: gigasmol
Version: 0.0.8
Summary: A lightweight wrapper for gigachat api model for seamless use with hf smolagents
Author-email: poteminr <poteminr@gmail.com>
License: LICENSE
Project-URL: Homepage, https://github.com/poteminr/gigasmol
Project-URL: Bug Tracker, https://github.com/poteminr/gigasmol/issues
Requires-Python: >=3.8
License-File: LICENSE
Requires-Dist: requests>=2.31.0
Requires-Dist: sseclient>=0.0.27
Requires-Dist: urllib3>=2.0.0
Provides-Extra: agent
Requires-Dist: smolagents==1.22.0; python_version >= "3.10" and extra == "agent"
Requires-Dist: huggingface-hub>=0.19.0; python_version >= "3.10" and extra == "agent"
Requires-Dist: gigasmol-agent-requires-python-3.10-or-newer==0.0.0; python_version < "3.10" and extra == "agent"
Dynamic: license-file
